sqeleton/__init__.py
sqeleton/__main__.py
sqeleton/abcs/__init__.py
sqeleton/abcs/compiler.py
sqeleton/abcs/database_types.py
sqeleton/abcs/mixins.py
sqeleton/bound_exprs.py
sqeleton/conn_editor.py
sqeleton/databases/__init__.py
sqeleton/databases/_connect.py
sqeleton/databases/base.py
sqeleton/databases/bigquery.py
sqeleton/databases/clickhouse.py
sqeleton/databases/databricks.py
sqeleton/databases/duckdb.py
sqeleton/databases/mssql.py
sqeleton/databases/mysql.py
sqeleton/databases/oracle.py
sqeleton/databases/postgresql.py
sqeleton/databases/presto.py
sqeleton/databases/redshift.py
sqeleton/databases/snowflake.py
sqeleton/databases/trino.py
sqeleton/databases/vertica.py
sqeleton/queries/__init__.py
sqeleton/queries/api.py
sqeleton/queries/ast_classes.py
sqeleton/queries/base.py
sqeleton/queries/compiler.py
sqeleton/queries/extras.py
sqeleton/query_utils.py
sqeleton/repl.py
sqeleton/schema.py
sqeleton/utils.py
sqeleton-0.1.7.dist-info/LICENSE
sqeleton-0.1.7.dist-info/METADATA
sqeleton-0.1.7.dist-info/WHEEL
sqeleton-0.1.7.dist-info/entry_points.txt
sqeleton-0.1.7.dist-info/RECORD
