Metadata-Version: 2.1
Name: sqeleton
Version: 0.1.7
Summary: Python library for querying SQL databases
Home-page: https://github.com/erezsh/sqeleton
License: MIT
Author: Erez Shinan
Author-email: erezshin@gmail.com
Requires-Python: >=3.8,<4.0
Classifier: Development Status :: 2 - Pre-Alpha
Classifier: Environment :: Console
Classifier: Intended Audience :: Developers
Classifier: Intended Audience :: Information Technology
Classifier: Intended Audience :: System Administrators
Classifier: License :: OSI Approved :: MIT License
Classifier: Programming Language :: Python :: 3
Classifier: Programming Language :: Python :: 3.8
Classifier: Programming Language :: Python :: 3.9
Classifier: Programming Language :: Python :: 3.10
Classifier: Programming Language :: Python :: 3.11
Classifier: Programming Language :: Python :: 3.12
Classifier: Topic :: Database :: Database Engines/Servers
Classifier: Typing :: Typed
Provides-Extra: clickhouse
Provides-Extra: databricks
Provides-Extra: duckdb
Provides-Extra: mysql
Provides-Extra: oracle
Provides-Extra: postgresql
Provides-Extra: presto
Provides-Extra: snowflake
Provides-Extra: trino
Provides-Extra: tui
Provides-Extra: vertica
Requires-Dist: click (>=8.1)
Requires-Dist: clickhouse-driver ; extra == "clickhouse"
Requires-Dist: cryptography ; extra == "snowflake"
Requires-Dist: dsnparse
Requires-Dist: duckdb (>=0.7.0) ; extra == "duckdb"
Requires-Dist: mysql-connector-python (>=8.0.29) ; extra == "mysql"
Requires-Dist: presto-python-client ; extra == "presto"
Requires-Dist: prompt-toolkit (>=3.0.36) ; extra == "tui"
Requires-Dist: psycopg2-binary ; extra == "postgresql"
Requires-Dist: pygments (>=2.13.0) ; extra == "tui"
Requires-Dist: rich
Requires-Dist: runtype (>=0.5.0)
Requires-Dist: snowflake-connector-python (>=2.7.2) ; extra == "snowflake"
Requires-Dist: textual (>=0.9.1) ; extra == "tui"
Requires-Dist: textual-select ; extra == "tui"
Requires-Dist: toml (>=0.10.2)
Requires-Dist: trino (>=0.314.0) ; extra == "trino"
Project-URL: Documentation, https://sqeleton.readthedocs.io/en/latest/
Project-URL: Repository, https://github.com/erezsh/sqeleton
